fluent_selectors/__init__.py
fluent_selectors/py.typed
fluent_selectors-0.1.8.dist-info/WHEEL
fluent_selectors-0.1.8.dist-info/METADATA
fluent_selectors-0.1.8.dist-info/RECORD
