Metadata-Version: 2.3
Name: fluent-selectors
Version: 0.1.8
Summary: A Python library for creating a readable, fluent API for Selenium browser automation
Keywords: fluent,selectors,testing,assertions,validation
Author: vantorrewannes
Author-email: vantorrewannes <vantorrewannes@gmail.com>
Classifier: Programming Language :: Python :: 3
Classifier: Operating System :: OS Independent
Classifier: Development Status :: 3 - Alpha
Classifier: Intended Audience :: Developers
Classifier: Topic :: Software Development :: Testing
Classifier: Topic :: Utilities
Requires-Dist: fluent-checks>=0.3.0
Requires-Dist: selenium>=4.35.0
Requires-Python: >=3.12
Project-URL: Bug Tracker, https://github.com/VantorreWannes/fluent-selectors/issues
Project-URL: Homepage, https://github.com/VantorreWannes/fluent-selectors
